extendable/__init__.py
extendable/context.py
extendable/exceptions.py
extendable/main.py
extendable/py.typed
extendable/registry.py
extendable/utils.py
extendable/version.py
extendable-1.3.0.dist-info/licenses/LICENSE
extendable-1.3.0.dist-info/WHEEL
extendable-1.3.0.dist-info/METADATA
extendable-1.3.0.dist-info/RECORD
