Metadata-Version: 2.4
Name: extendable
Version: 1.3.0
Summary: A lib to define class extendable at runtime.
Author-email: Laurent Mignon <laurent.mignon@acsone.eu>
Requires-Python: >=3.6
Classifier: License :: OSI Approved :: MIT License
Classifier: Intended Audience :: Developers
Classifier: Operating System :: OS Independent
License-File: LICENSE
Requires-Dist: contextvars;python_version<'3.7'
Requires-Dist: types-contextvars;python_version<'3.7'
Requires-Dist: typing_extensions;python_version<'3.7'
Requires-Dist: mypy ; extra == "mypy"
Requires-Dist: towncrier ; extra == "release"
Requires-Dist: bumpversion ; extra == "release"
Requires-Dist: pytest ; extra == "test"
Requires-Dist: pytest-mock ; extra == "test"
Requires-Dist: coverage[toml] ; extra == "test"
Project-URL: Changelog, https://github.com/lmignon/extendable/blob/master/HISTORY.rst
Project-URL: Source, https://github.com/lmignon/extendable
Provides-Extra: mypy
Provides-Extra: release
Provides-Extra: test
